README.txt
setup.cfg
setup.py
Dwcm/Wordcloud.py
Dwcm/__init__.py
Dwcm/_imports_.py
Dwcm/dwcm.min.js
Dwcm/dwcm.min.js.map
Dwcm/metadata.json
Dwcm/output.js
Dwcm/output.js.map
Dwcm/package-info.json
Dwcm.egg-info/PKG-INFO
Dwcm.egg-info/SOURCES.txt
Dwcm.egg-info/dependency_links.txt
Dwcm.egg-info/requires.txt
Dwcm.egg-info/top_level.txt
dwcm/Wordcloud.py
dwcm/__init__.py
dwcm/_imports_.py
dwcm/dwcm.min.js
dwcm/dwcm.min.js.map
dwcm/metadata.json
dwcm/output.js
dwcm/output.js.map
dwcm/package-info.json
dwcm.egg-info/PKG-INFO
dwcm.egg-info/SOURCES.txt
dwcm.egg-info/dependency_links.txt
dwcm.egg-info/requires.txt
dwcm.egg-info/top_level.txt